MANIFEST.in
NEWS.txt
README.md
setup.cfg
setup.py
src/markovfsm/__init__.py
src/markovfsm/plot.py
src/markovfsm.egg-info/PKG-INFO
src/markovfsm.egg-info/SOURCES.txt
src/markovfsm.egg-info/dependency_links.txt
src/markovfsm.egg-info/not-zip-safe
src/markovfsm.egg-info/top_level.txt