Metadata-Version: 1.1
Name: markovfsm
Version: 0.2
Summary: Markov Chain generator from random process data
Home-page: https://github.com/vladignatyev/markovfsm
Author: Vladimir Ignatev
Author-email: ya.na.pochte@gmail.com
License: MIT
Keywords: markov chain random process probability stochastic automata finite-state machine fsm
Platform: UNKNOWN
Classifier: Development Status :: 3 - Alpha
Classifier: Intended Audience :: Developers
Classifier: Programming Language :: Python :: 2
Classifier: Programming Language :: Python :: 2.6
Classifier: Programming Language :: Python :: 2.7
Classifier: Programming Language :: Python :: 3
Classifier: Programming Language :: Python :: 3.2
Classifier: Programming Language :: Python :: 3.3
Classifier: Programming Language :: Python :: 3.4
Classifier: Topic :: Software Development :: Libraries
Classifier: Topic :: Scientific/Engineering :: Information Analysis
Classifier: Topic :: Scientific/Engineering :: Artificial Intelligence
Classifier: License :: CC0 1.0 Universal (CC0 1.0) Public Domain Dedication
Classifier: License :: OSI Approved :: MIT License
Classifier: Natural Language :: English
